pulkith_process_manager/DynamicPoolConfig.py
pulkith_process_manager/DynamicProcessPoolManager.py
pulkith_process_manager/EnhancedFuture.py
pulkith_process_manager/Example.py
pulkith_process_manager/Notes.md
pulkith_process_manager/PoolTask.py
pulkith_process_manager/PoolType.py
pulkith_process_manager/README.md
pulkith_process_manager/Todo.md
pulkith_process_manager/_AssignedUserPools.py
pulkith_process_manager/_DynamicProcessPoolStateInstance.py
pulkith_process_manager/_PoolTaskQueueAndManager.py
pulkith_process_manager/_PoolTypeMapping.py
pulkith_process_manager/_PoolUtilization.py
pulkith_process_manager/_PoolWrapper.py
pulkith_process_manager/_ProcessPoolUser.py
pulkith_process_manager/_TaskStatus.py
pulkith_process_manager-1.0.1.dist-info/METADATA
pulkith_process_manager-1.0.1.dist-info/WHEEL
pulkith_process_manager-1.0.1.dist-info/RECORD
