Metadata-Version: 2.1
Name: pulkith-process-manager
Version: 1.0.1
Summary: 
Author: Pulkith
Author-email: pulkith.pa@gmail.com
Requires-Python: >=3.11,<4.0
Classifier: Programming Language :: Python :: 3
Classifier: Programming Language :: Python :: 3.11
Classifier: Programming Language :: Python :: 3.12
Requires-Dist: asyncio (>=3.4.3,<4.0.0)
Requires-Dist: uuid (>=1.30,<2.0)
